LICENSE
MANIFEST.in
README.rst
setup.py
ddah_promises.egg-info/PKG-INFO
ddah_promises.egg-info/SOURCES.txt
ddah_promises.egg-info/dependency_links.txt
ddah_promises.egg-info/requires.txt
ddah_promises.egg-info/top_level.txt
promises/__init__.py
promises/admin.py
promises/models.py
promises/queryset.py
promises/csv_loader/__init__.py
promises/csv_loader/creator.py
promises/csv_loader/csv_processor.py
promises/csv_loader/processor.py