Metadata-Version: 1.1
Name: ddah-promises
Version: 0.0.6
Summary: Promises app.
Home-page: http://github.com/ciudadanointeligente/ddah-promises
Author: Felipe Álvarez / Juan Pablo Pérez Trabucco
Author-email: lab@ciudadanointeligente.org
License: Affero
Platform: UNKNOWN
Classifier: Environment :: Web Environment
Classifier: Framework :: Django
Classifier: Intended Audience :: Developers
Classifier: License :: OSI Approved :: GNU Affero General Public License v3
Classifier: Operating System :: OS Independent
Classifier: Programming Language :: Python
Classifier: Programming Language :: Python :: 2.6
Classifier: Programming Language :: Python :: 2.7
Classifier: Topic :: Internet :: WWW/HTTP
Classifier: Topic :: Internet :: WWW/HTTP :: Dynamic Content
